ctu_crs/__init__.py
ctu_crs/crs93.py
ctu_crs/crs97.py
ctu_crs/crs_robot.py
ctu_crs/gripper.py
ctu_crs/params_crs93.yaml
ctu_crs/params_crs97.yaml
ctu_crs/scripts/move_crs93.py
ctu_crs/scripts/move_crs97.py
ctu_crs-1.0.5.dist-info/licenses/LICENSE
ctu_crs-1.0.5.dist-info/METADATA
ctu_crs-1.0.5.dist-info/WHEEL
ctu_crs-1.0.5.dist-info/entry_points.txt
ctu_crs-1.0.5.dist-info/top_level.txt
ctu_crs-1.0.5.dist-info/RECORD
